pyatmo/__init__.py
pyatmo/account.py
pyatmo/auth.py
pyatmo/const.py
pyatmo/enums.py
pyatmo/event.py
pyatmo/exceptions.py
pyatmo/helpers.py
pyatmo/home.py
pyatmo/person.py
pyatmo/py.typed
pyatmo/room.py
pyatmo/schedule.py
pyatmo/modules/__init__.py
pyatmo/modules/base_class.py
pyatmo/modules/bticino.py
pyatmo/modules/device_types.py
pyatmo/modules/idiamant.py
pyatmo/modules/legrand.py
pyatmo/modules/module.py
pyatmo/modules/netatmo.py
pyatmo/modules/smarther.py
pyatmo/modules/somfy.py
pyatmo-9.2.3.dist-info/licenses/LICENSE.txt
pyatmo-9.2.3.dist-info/METADATA
pyatmo-9.2.3.dist-info/WHEEL
pyatmo-9.2.3.dist-info/top_level.txt
pyatmo-9.2.3.dist-info/RECORD
