Metadata-Version: 2.4
Name: pyatmo
Version: 9.2.3
Summary: Simple API to access Netatmo weather station data from any Python 3 script. Designed for Home Assistant (but not only)
Author-email: Hugo Dupras <jabesq@gmail.com>
Maintainer-email: Tobias Sauerwein <cgtobi@gmail.com>, Hugo Dupras <jabesq@gmail.com>
License-Expression: MIT
Project-URL: Changelog, https://github.com/jabesq-org/pyatmo/blob/development/CHANGELOG.md
Project-URL: Homepage, https://github.com/jabesq-org/pyatmo
Project-URL: Issues, https://github.com/jabesq-org/pyatmo/issues
Project-URL: Repository, https://github.com/jabesq-org/pyatmo.git
Classifier: Development Status :: 5 - Production/Stable
Classifier: Intended Audience :: Developers
Classifier: Programming Language :: Python :: 3
Classifier: Programming Language :: Python :: 3 :: Only
Classifier: Programming Language :: Python :: Implementation :: CPython
Classifier: Programming Language :: Python :: Implementation :: PyPy
Classifier: Topic :: Home Automation
Requires-Python: >=3.11
License-File: LICENSE.txt
Requires-Dist: aiohttp<4.0.0,>=3.7.4
Requires-Dist: oauthlib~=3.1
Requires-Dist: requests-oauthlib<3.0,>=1.3
Requires-Dist: requests~=2.24
Dynamic: license-file
